LICENSE.txt
README.md
pyproject.toml
setup.py
django_kibrudashboard/__init__.py
django_kibrudashboard/apps.py
django_kibrudashboard/compat.py
django_kibrudashboard/settings.py
django_kibrudashboard/urls.py
django_kibrudashboard/utils.py
django_kibrudashboard/views.py
django_kibrudashboard/widgets.py
django_kibrudashboard.egg-info/PKG-INFO
django_kibrudashboard.egg-info/SOURCES.txt
django_kibrudashboard.egg-info/dependency_links.txt
django_kibrudashboard.egg-info/requires.txt
django_kibrudashboard.egg-info/top_level.txt
django_kibrudashboard/templatetags/__init__.py
django_kibrudashboard/templatetags/django_kibrudashboard.py