Metadata-Version: 2.1
Name: django-kibrudashboard
Version: 1.1.0
Summary: Django dashboard 
Home-page: UNKNOWN
Author: Kibru (DevKibru)
Author-email: <kibrug474@gmail.com>
License: UNKNOWN
Keywords: python,kibru,django,django_kibrudashboard,django-kibru
Platform: UNKNOWN
Classifier: Development Status :: 1 - Planning
Classifier: Intended Audience :: Developers
Classifier: Programming Language :: Python :: 3
Classifier: Operating System :: Unix
Classifier: Operating System :: MacOS :: MacOS X
Classifier: Operating System :: Microsoft :: Windows
License-File: LICENSE.txt
